selenium_selector_autocorrect/__init__.py
selenium_selector_autocorrect/ai_providers.py
selenium_selector_autocorrect/auto_correct.py
selenium_selector_autocorrect/correction_tracker.py
selenium_selector_autocorrect/wait_hook.py
selenium_selector_autocorrect-0.1.1.dist-info/licenses/LICENSE
selenium_selector_autocorrect-0.1.1.dist-info/METADATA
selenium_selector_autocorrect-0.1.1.dist-info/WHEEL
selenium_selector_autocorrect-0.1.1.dist-info/top_level.txt
selenium_selector_autocorrect-0.1.1.dist-info/RECORD
