Metadata-Version: 2.4
Name: selenium-selector-autocorrect
Version: 0.1.1
Summary: Automatic Selenium selector correction using AI when elements fail to be found
Author-email: Marty Zhou <marty.zhou@example.com>
Maintainer-email: Marty Zhou <marty.zhou@example.com>
License: MIT
Project-URL: Homepage, https://github.com/MartyZhou/selenium-selector-autocorrect
Project-URL: Documentation, https://github.com/MartyZhou/selenium-selector-autocorrect#readme
Project-URL: Repository, https://github.com/MartyZhou/selenium-selector-autocorrect
Project-URL: Issues, https://github.com/MartyZhou/selenium-selector-autocorrect/issues
Project-URL: Changelog, https://github.com/MartyZhou/selenium-selector-autocorrect/blob/main/CHANGELOG.md
Keywords: selenium,testing,automation,ai,web-testing,test-automation,selector,auto-correction
Classifier: Development Status :: 4 - Beta
Classifier: Intended Audience :: Developers
Classifier: License :: OSI Approved :: MIT License
Classifier: Operating System :: OS Independent
Classifier: Programming Language :: Python :: 3
Classifier: Programming Language :: Python :: 3.8
Classifier: Programming Language :: Python :: 3.9
Classifier: Programming Language :: Python :: 3.10
Classifier: Programming Language :: Python :: 3.11
Classifier: Programming Language :: Python :: 3.12
Classifier: Topic :: Software Development :: Testing
Classifier: Topic :: Software Development :: Quality Assurance
Classifier: Framework :: Pytest
Requires-Python: >=3.8
License-File: LICENSE
Requires-Dist: selenium>=4.0.0
Requires-Dist: requests>=2.25.0
Provides-Extra: dev
Requires-Dist: pytest>=7.0.0; extra == "dev"
Requires-Dist: pytest-cov>=4.0.0; extra == "dev"
Requires-Dist: black>=23.0.0; extra == "dev"
Requires-Dist: isort>=5.12.0; extra == "dev"
Requires-Dist: mypy>=1.0.0; extra == "dev"
Requires-Dist: ruff>=0.1.0; extra == "dev"
Dynamic: license-file
